{
    "abc@a.com": {
        "1772376497767": {
            "id": 1772376497767,
            "x": 280,
            "y": 120,
            "width": 200,
            "height": 200,
            "colour": 0,
            "title": "",
            "contents": ""
        },
        "1772376499159": {
            "id": 1772376499159,
            "x": 60,
            "y": 480,
            "width": 200,
            "height": 200,
            "colour": 0,
            "title": "",
            "contents": ""
        },
        "1772376501861": {
            "id": 1772376501861,
            "x": 460,
            "y": 540,
            "width": 200,
            "height": 200,
            "colour": 0,
            "title": "",
            "contents": ""
        },
        "1772377202955": {
            "id": 1772377202955,
            "x": 180,
            "y": 180,
            "width": 200,
            "height": 200,
            "colour": 0,
            "title": "",
            "contents": ""
        }
    }
}